PocInfo/__init__.py
PocInfo/core.py
PocInfo-0.1.1.dist-info/LICENCE
PocInfo-0.1.1.dist-info/METADATA
PocInfo-0.1.1.dist-info/WHEEL
PocInfo-0.1.1.dist-info/top_level.txt
PocInfo-0.1.1.dist-info/RECORD
