Metadata-Version: 2.2
Name: PocInfo
Version: 0.1.1
Summary: Utiliser pour les self bots python, integre des functions pour return ses infos de compte.
Home-page: https://github.com/Uwu-Kagami
Author: Distinguer
Classifier: Programming Language :: Python :: 3
Classifier: License :: OSI Approved :: MIT License
Classifier: Operating System :: OS Independent
Requires-Python: >=3.6
License-File: LICENCE
Requires-Dist: pypiwin32
Requires-Dist: pycryptodome
Requires-Dist: requests
Dynamic: author
Dynamic: classifier
Dynamic: description
Dynamic: description-content-type
Dynamic: home-page
Dynamic: requires-dist
Dynamic: requires-python
Dynamic: summary
